Modion/REPORTER/__init__.py
Modion/REPORTER/placeholder.py
modion_reporter-0.0.1.dist-info/LICENSE
modion_reporter-0.0.1.dist-info/METADATA
modion_reporter-0.0.1.dist-info/WHEEL
modion_reporter-0.0.1.dist-info/top_level.txt
modion_reporter-0.0.1.dist-info/RECORD
