Metadata-Version: 2.2
Name: Modion.REPORTER
Version: 0.0.1
Summary: Python API for Modion REPORTER
Author: Miles Thornton
Maintainer-email: dyna.support@arup.com
License: MIT License
Project-URL: Homepage, https://www.oasys-software.com/dyna/
Keywords: Modion,REPORTER
Requires-Python: >=3.7
License-File: LICENSE
Requires-Dist: Modion.gRPC
